CHANGES.rst
LICENSE
MANIFEST.in
README
setup.py
doc/conf.py
doc/index.rst
sphinxcontrib/__init__.py
sphinxcontrib/scaladomain.py
sphinxcontrib_scaladomain.egg-info/PKG-INFO
sphinxcontrib_scaladomain.egg-info/SOURCES.txt
sphinxcontrib_scaladomain.egg-info/dependency_links.txt
sphinxcontrib_scaladomain.egg-info/namespace_packages.txt
sphinxcontrib_scaladomain.egg-info/not-zip-safe
sphinxcontrib_scaladomain.egg-info/requires.txt
sphinxcontrib_scaladomain.egg-info/top_level.txt
tests/acceptance/conf.py
tests/acceptance/index.rst