Metadata-Version: 1.0
Name: sphinxcontrib-scaladomain
Version: 0.1a1
Summary: Sphinx domain for Scala APIs
Home-page: http://bitbucket.org/birkenfeld/sphinx-contrib
Author: Georges Discry
Author-email: georges@discry.be
License: BSD
Download-URL: http://pypi.python.org/pypi/sphinxcontrib-scaladomain
Platform: any
Classifier: Development Status :: 3 - Alpha
Classifier: Environment :: Console
Classifier: Environment :: Web Environment
Classifier: Intended Audience :: Developers
Classifier: License :: OSI Approved :: BSD License
Classifier: Operating System :: OS Independent
Classifier: Programming Language :: Python
Classifier: Programming Language :: Python :: 2
Classifier: Programming Language :: Python :: 3
Classifier: Topic :: Documentation
Classifier: Topic :: Utilities
